.gitignore
LICENSE
README.md
Web Scrapping on LyricWiki.ipynb
requirements.txt
setup.py
.idea/.gitignore
.idea/misc.xml
.idea/modules.xml
.idea/scrape-lyricswiki.iml
.idea/vcs.xml
.idea/inspectionProfiles/profiles_settings.xml
docs/Makefile
docs/conf.py
docs/index.rst
docs/make.bat
docs/source/example.rst
docs/source/getting-started.rst
docs/source/package.rst
docs/source/image/comparison.png
docs/source/image/lyricsfandom.png
img/comparison.png
img/lyricsfandom.png
lyricsfandom/__init__.py
lyricsfandom/api.py
lyricsfandom/connect.py
lyricsfandom/meta.py
lyricsfandom/scrape.py
lyricsfandom/utils.py
lyricsfandom.egg-info/PKG-INFO
lyricsfandom.egg-info/SOURCES.txt
lyricsfandom.egg-info/dependency_links.txt
lyricsfandom.egg-info/not-zip-safe
lyricsfandom.egg-info/requires.txt
lyricsfandom.egg-info/top_level.txt
lyricsfandom/music/__init__.py
lyricsfandom/music/album.py
lyricsfandom/music/artist.py
lyricsfandom/music/song.py