Metadata-Version: 2.1
Name: lyricsfandom
Version: 0.2.1
Summary: Scrape songs on LyricWiki.
Home-page: https://github.com/arthurdjn/scrape-lyricwiki
Author: Arthur Dujardin
Author-email: arthur.dujardin@ensg.eu
License: MIT Licence
Platform: UNKNOWN
Classifier: Development Status :: 5 - Production/Stable
Classifier: Intended Audience :: Developers
Classifier: Topic :: Software Development :: Build Tools
Classifier: License :: OSI Approved :: MIT License
Classifier: Programming Language :: Python :: 3
Classifier: Programming Language :: Python :: 3.4
Classifier: Programming Language :: Python :: 3.5
Classifier: Programming Language :: Python :: 3.6
